[
  {
    "type": "overmap_location",
    "id": "isekai_trail",
    "terrains": [ "isekai_trail" ]
  },
  {
    "type": "overmap_location",
    "id": "isekai_field",
    "terrains": [ "isekai_field" ]
  },
  {
    "type": "overmap_connection",
    "id": "isekai_trail",
    "subtypes": [
      { "terrain": "isekai_trail", "locations": [ "isekai_field", "isekai_trail" ] },
      { "terrain": "isekai_trail", "locations": [ "forest" ], "basic_cost": 5 },
      { "terrain": "isekai_trail", "locations": [ "swamp" ], "basic_cost": 40 },
      { "terrain": "isekai_bridge_road", "locations": [ "water" ], "basic_cost": 120, "flags": [ "ORTHOGONAL" ] }
    ]
  }
]
