[
  {
    "type": "region_settings",
    "id": "isekai",
    "rivers": "default",
    "lakes": "default",
    "ocean": null,
    "ravines": "default",
    "forests": "default",
    "forest_composition": "default",
    "forest_trails": "isekai_default",
    "highways": null,
    "cities": "isekai_default",
    "map_extras": "no_map_extras",
    "terrain_furniture": "default",
    "weather": "default",
    "urbanity_increase": [ 0, 10, 5, 0 ],
    "default_oter": [
      "open_air",
      "open_air",
      "open_air",
      "open_air",
      "open_air",
      "open_air",
      "open_air",
      "open_air",
      "open_air",
      "open_air",
      "field",
      "solid_earth",
      "empty_rock",
      "empty_rock",
      "deep_rock",
      "deep_rock",
      "deep_rock",
      "deep_rock",
      "deep_rock",
      "deep_rock",
      "deep_rock"
    ],
    "default_groundcover": [ [ "t_region_groundcover", 1 ] ],
    "feature_flag_settings": { "blacklist": [  ], "whitelist": [ "ISEKAI" ] },
    "connections": {
      "intra_city_road_connection": "local_road",
      "inter_city_road_connection": "local_road",
      "trail_connection": "forest_trail",
      "sewer_connection": "sewer_tunnel",
      "subway_connection": "subway_tunnel",
      "rail_connection": "local_railroad"
    }
  },
  {
    "type": "region_settings_forest_trail",
    "id": "isekai_default",
    "copy-from": "default",
    "chance": 20,
    "border_point_chance": 2,
    "minimum_forest_size": 20,
    "random_point_min": 4,
    "random_point_max": 50,
    "random_point_size_scalar": 100,
    "trailhead_chance": 1,
    "trailhead_road_distance": 6,
    "trailheads": [ [ "trailhead_basic", 1 ] ]
  },
  {
    "type": "region_settings_city",
    "id": "isekai_default",
    "shop_radius": 0,
    "shop_sigma": 0,
    "park_radius": 0,
    "park_sigma": 0,
    "houses": [ [ "isekai_cabin_1", 50 ] ],
    "parks": [  ],
    "shops": [  ]
  }
]
